Workbook

Sheet README_Assumptions
A1: Lab 3B: Advanced Cybersecurity Risk Quantification - SecureBank Financial
A2: Student: Chioma Ameh | Registration number: C11/26/CGRCE/17567 | Course: GRC103 | Date: 29 October 2026 (WAT)
A4: Colour legend
A5: Blue text | B5: Input copied from the lab sheet, or an input you may change (all figures flow through by formula).
A6: Black text | B6: Calculated by formula.
A7: Green text | B7: Pulled from another sheet by formula.
A8: Yellow fill | B8: Assumption chosen by the analyst (not given in the lab sheet). Change it and everything recalculates.
A10: Sheet guide
A11: Inputs | B11: Every given number and every assumption, in one place.
A12: Phase1_ALE | B12: Task 1 (SLE, ARO, ALE) and Task 2 (risk prioritisation matrix).
A13: Heat_Map | B13: Task 3 risk heat map (probability x impact).
A14: Phase2_Controls | B14: Task 4 cost-benefit: investment, maintenance, risk reduction, ROI, payback.
A15: Timeline | B15: Task 5 risk reduction over time (line graph data).
A16: Budget | B16: Bonus: combined risk-control matrix and optimal selection under budget limits.
A17: Gantt | B17: Task 7 risk treatment timeline (Gantt chart).
A18: Charts | B18: All required graphs: bar, pie, scatter, ROI horizontal bar, before/after double bar, stacked bar, line.
A20: Assumptions and decisions (documented for CISO and CFO review)
A21: A1 Given | B21: Exploit probabilities, loss figures, control costs, effectiveness and maintenance come from the Lab 3B sheet.
A22: A2 Assumed | B22: ARO equals the exploit probability treated as a yearly rate: 15% = 0.15 expected incidents per year. The sheet does not say 'per year'.
A23: A3 Assumed | B23: SLE uses the sheet loss figures directly. Finding 1: the stated maximum single incident loss. Finding 2: 500,000 records x $250. Finding 3: 5,000 accounts x $1,500. No exposure factor is given, so none is applied.
A24: A4 Assumed | B24: Each control mitigates the finding it is designed for: API Gateway to Finding 1, WAF to Finding 2, MFA to Finding 3. Its effectiveness applies to that finding's ALE only. The sheet states MFA effectiveness for 'account takeover' and it is applied to session hijacking.
A25: A5 Assumed | B25: ROI is shown two ways: on initial investment (the class formula, benefits minus cost over cost) and on Year-1 total cost (initial plus first-year maintenance). Benefit = annual risk reduction. Payback = initial investment / (annual risk reduction - annual maintenance).
A26: A6 Assumed | B26: Probability, impact and heat-score thresholds are the yellow cells on the Inputs sheet. Heat map cell colours are fixed to the standard 3x3 pattern.
A27: A7 Assumed | B27: The sheet gives no budget limit. $500,000 is used as the main constrained scenario and other budgets are tested as well.
A28: A8 Not used | B28: System context (500,000 users, $2,500 average transaction, 50,000 daily transactions, 48-hour detection for Finding 1) is kept as context. The sheet supplies loss figures directly.
A29: A9 Proposal | B29: The Gantt timeline is the analyst's proposed plan, not data from the lab sheet. Budget per task adds up to the total initial investment.
A30: A10 AI use | B30: Prepared with guidance from Claude (Anthropic). Formulas were recalculated and every result was checked independently against hand calculations.

Sheet Inputs
A1: Inputs (given data and assumptions)
A2: Blue = given in the lab sheet. Yellow = analyst assumption.
A3: ID | B3: Vulnerability | C3: Exploit probability (ARO per year) | D3: Units at risk | E3: Loss per unit ($) | F3: Direct SLE ($) | G3: Mapped control
A4: F1 | B4: API Authentication Bypass | C4: 0.15 | F4: 5000000 | G4: Advanced API Security Gateway
A5: F2 | B5: Database Injection | C5: 0.25 | D5: 500000 | E5: 250 | G5: Web Application Firewall (WAF)
A6: F3 | B6: Session Hijacking | C6: 0.4 | D6: 5000 | E6: 1500 | G6: Multi-Factor Authentication Enhancement
A9: ID | B9: Control | C9: Initial investment ($) | D9: Annual maintenance ($/yr) | E9: Effectiveness | F9: Mitigates finding
A10: C1 | B10: Advanced API Security Gateway | C10: 350000 | D10: 50000 | E10: 0.9 | F10: F1
A11: C2 | B11: Web Application Firewall (WAF) | C11: 150000 | D11: 25000 | E11: 0.75 | F11: F2
A12: C3 | B12: Multi-Factor Authentication Enhancement | C12: 200000 | D12: 30000 | E12: 0.95 | F12: F3
A14: Assumed thresholds and settings
A15: Probability: High if at least | B15: 0.3
A16: Probability: Medium if at least | B16: 0.1
A17: Impact (SLE): High if at least ($) | B17: 10000000
A18: Impact (SLE): Medium if at least ($) | B18: 1000000
A19: Heat score: High if at least | B19: 6
A20: Heat score: Medium if at least | B20: 3
A21: Analysis horizon (years) | B21: 3
A22: Constrained budget for bonus ($) | B22: 500000
A24: System context (not used in formulas)
A25: Active customers | B25: 500000
A26: Average transaction ($) | B26: 2500
A27: Daily transactions | B27: 50000
A28: Finding 1 estimated detection (hours) | B28: 48
A30: Heat score = probability score x impact score, where Low = 1, Medium = 2, High = 3.

Sheet Phase1_ALE
A1: Phase 1: Risk exposure (Task 1) and prioritisation matrix (Task 2)
A2: SLE = loss from one incident. ARO = incidents per year. ALE = SLE x ARO.
A4: ID | B4: Vulnerability | C4: SLE ($) | D4: ARO (per year) | E4: ALE ($ per year) | F4: Share of total ALE | G4: Rank by ALE | H4: Probability level | I4: Impact level | J4: Heat score | K4: Risk Priority Level
A5: =Inputs!A4 -> F1 | B5: =Inputs!B4 -> API Authentication Bypass | C5: =IF(Inputs!F4<>"",Inputs!F4,Inputs!D4*Inputs!E4) -> 5000000 | D5: =Inputs!C4 -> 0.15 | E5: =C5*D5 -> 750000 | F5: =E5/$E$8 -> 0.021428571 | G5: =RANK(E5,$E$5:$E$7,0) -> 3 | H5: =IF(D5>=Inputs!$B$15,"High",IF(D5>=Inputs!$B$16,"Medium","Low")) -> Medium | I5: =IF(C5>=Inputs!$B$17,"High",IF(C5>=Inputs!$B$18,"Medium","Low")) -> Medium | J5: =IF(H5="High",3,IF(H5="Medium",2,1))*IF(I5="High",3,IF(I5="Medium",2,1)) -> 4 | K5: =IF(J5>=Inputs!$B$19,"High",IF(J5>=Inputs!$B$20,"Medium","Low")) -> Medium
A6: =Inputs!A5 -> F2 | B6: =Inputs!B5 -> Database Injection | C6: =IF(Inputs!F5<>"",Inputs!F5,Inputs!D5*Inputs!E5) -> 125000000 | D6: =Inputs!C5 -> 0.25 | E6: =C6*D6 -> 31250000 | F6: =E6/$E$8 -> 0.89285714 | G6: =RANK(E6,$E$5:$E$7,0) -> 1 | H6: =IF(D6>=Inputs!$B$15,"High",IF(D6>=Inputs!$B$16,"Medium","Low")) -> Medium | I6: =IF(C6>=Inputs!$B$17,"High",IF(C6>=Inputs!$B$18,"Medium","Low")) -> High | J6: =IF(H6="High",3,IF(H6="Medium",2,1))*IF(I6="High",3,IF(I6="Medium",2,1)) -> 6 | K6: =IF(J6>=Inputs!$B$19,"High",IF(J6>=Inputs!$B$20,"Medium","Low")) -> High
A7: =Inputs!A6 -> F3 | B7: =Inputs!B6 -> Session Hijacking | C7: =IF(Inputs!F6<>"",Inputs!F6,Inputs!D6*Inputs!E6) -> 7500000 | D7: =Inputs!C6 -> 0.4 | E7: =C7*D7 -> 3000000 | F7: =E7/$E$8 -> 0.085714286 | G7: =RANK(E7,$E$5:$E$7,0) -> 2 | H7: =IF(D7>=Inputs!$B$15,"High",IF(D7>=Inputs!$B$16,"Medium","Low")) -> High | I7: =IF(C7>=Inputs!$B$17,"High",IF(C7>=Inputs!$B$18,"Medium","Low")) -> Medium | J7: =IF(H7="High",3,IF(H7="Medium",2,1))*IF(I7="High",3,IF(I7="Medium",2,1)) -> 6 | K7: =IF(J7>=Inputs!$B$19,"High",IF(J7>=Inputs!$B$20,"Medium","Low")) -> High
A8: Total | E8: =SUM(E5:E7) -> 35000000 | F8: =SUM(F5:F7) -> 1
A11: Risk prioritisation matrix (sorted by ALE, highest first)
A12: Rank | B12: Vulnerability | C12: SLE ($) | D12: ARO | E12: ALE ($ per year) | F12: Share of total | H12: Probability | I12: Impact | K12: Risk Priority Level
A13: 1 | B13: =INDEX($B$5:$B$7,MATCH($A13,$G$5:$G$7,0)) -> Database Injection | C13: =INDEX($C$5:$C$7,MATCH($A13,$G$5:$G$7,0)) -> 125000000 | D13: =INDEX($D$5:$D$7,MATCH($A13,$G$5:$G$7,0)) -> 0.25 | E13: =INDEX($E$5:$E$7,MATCH($A13,$G$5:$G$7,0)) -> 31250000 | F13: =INDEX($F$5:$F$7,MATCH($A13,$G$5:$G$7,0)) -> 0.89285714 | H13: =INDEX($H$5:$H$7,MATCH($A13,$G$5:$G$7,0)) -> Medium | I13: =INDEX($I$5:$I$7,MATCH($A13,$G$5:$G$7,0)) -> High | K13: =INDEX($K$5:$K$7,MATCH($A13,$G$5:$G$7,0)) -> High
A14: 2 | B14: =INDEX($B$5:$B$7,MATCH($A14,$G$5:$G$7,0)) -> Session Hijacking | C14: =INDEX($C$5:$C$7,MATCH($A14,$G$5:$G$7,0)) -> 7500000 | D14: =INDEX($D$5:$D$7,MATCH($A14,$G$5:$G$7,0)) -> 0.4 | E14: =INDEX($E$5:$E$7,MATCH($A14,$G$5:$G$7,0)) -> 3000000 | F14: =INDEX($F$5:$F$7,MATCH($A14,$G$5:$G$7,0)) -> 0.085714286 | H14: =INDEX($H$5:$H$7,MATCH($A14,$G$5:$G$7,0)) -> High | I14: =INDEX($I$5:$I$7,MATCH($A14,$G$5:$G$7,0)) -> Medium | K14: =INDEX($K$5:$K$7,MATCH($A14,$G$5:$G$7,0)) -> High
A15: 3 | B15: =INDEX($B$5:$B$7,MATCH($A15,$G$5:$G$7,0)) -> API Authentication Bypass | C15: =INDEX($C$5:$C$7,MATCH($A15,$G$5:$G$7,0)) -> 5000000 | D15: =INDEX($D$5:$D$7,MATCH($A15,$G$5:$G$7,0)) -> 0.15 | E15: =INDEX($E$5:$E$7,MATCH($A15,$G$5:$G$7,0)) -> 750000 | F15: =INDEX($F$5:$F$7,MATCH($A15,$G$5:$G$7,0)) -> 0.021428571 | H15: =INDEX($H$5:$H$7,MATCH($A15,$G$5:$G$7,0)) -> Medium | I15: =INDEX($I$5:$I$7,MATCH($A15,$G$5:$G$7,0)) -> Medium | K15: =INDEX($K$5:$K$7,MATCH($A15,$G$5:$G$7,0)) -> Medium
A17: Priority level comes from the heat score (probability x impact, thresholds on the Inputs sheet). Rank breaks ties between levels using ALE.

Sheet Heat_Map
A1: Task 3: Risk heat map (probability x impact)
B3: IMPACT (single-incident loss, SLE) | F3: Findings plotted
A4: PROBABILITY (ARO) | B4: Low | C4: Medium | D4: High | F4: Finding | G4: Probability | H4: Impact
A5: High | B5: =TRIM(IF(AND(Phase1_ALE!$H$5=$A5,Phase1_ALE!$I$5=B$4),Phase1_ALE!$A$5&" ","")&IF(AND(Phase1_ALE!$H$6=$A5,Phase1_ALE!$I$6=B$4),Phase1_ALE!$A$6&" ","")&IF(AND(Phase1_ALE!$H$7=$A5,Phase1_ALE!$I$7=B$4),Phase1_ALE!$A$7&" ","")) | C5: =TRIM(IF(AND(Phase1_ALE!$H$5=$A5,Phase1_ALE!$I$5=C$4),Phase1_ALE!$A$5&" ","")&IF(AND(Phase1_ALE!$H$6=$A5,Phase1_ALE!$I$6=C$4),Phase1_ALE!$A$6&" ","")&IF(AND(Phase1_ALE!$H$7=$A5,Phase1_ALE!$I$7=C$4),Phase1_ALE!$A$7&" ","")) -> F3 | D5: =TRIM(IF(AND(Phase1_ALE!$H$5=$A5,Phase1_ALE!$I$5=D$4),Phase1_ALE!$A$5&" ","")&IF(AND(Phase1_ALE!$H$6=$A5,Phase1_ALE!$I$6=D$4),Phase1_ALE!$A$6&" ","")&IF(AND(Phase1_ALE!$H$7=$A5,Phase1_ALE!$I$7=D$4),Phase1_ALE!$A$7&" ","")) | F5: =Phase1_ALE!A5&" - "&Phase1_ALE!B5 -> F1 - API Authentication Bypass | G5: =Phase1_ALE!H5&" ("&TEXT(Phase1_ALE!D5,"0%")&")" -> Medium (15%) | H5: =Phase1_ALE!I5 -> Medium
A6: Medium | B6: =TRIM(IF(AND(Phase1_ALE!$H$5=$A6,Phase1_ALE!$I$5=B$4),Phase1_ALE!$A$5&" ","")&IF(AND(Phase1_ALE!$H$6=$A6,Phase1_ALE!$I$6=B$4),Phase1_ALE!$A$6&" ","")&IF(AND(Phase1_ALE!$H$7=$A6,Phase1_ALE!$I$7=B$4),Phase1_ALE!$A$7&" ","")) | C6: =TRIM(IF(AND(Phase1_ALE!$H$5=$A6,Phase1_ALE!$I$5=C$4),Phase1_ALE!$A$5&" ","")&IF(AND(Phase1_ALE!$H$6=$A6,Phase1_ALE!$I$6=C$4),Phase1_ALE!$A$6&" ","")&IF(AND(Phase1_ALE!$H$7=$A6,Phase1_ALE!$I$7=C$4),Phase1_ALE!$A$7&" ","")) -> F1 | D6: =TRIM(IF(AND(Phase1_ALE!$H$5=$A6,Phase1_ALE!$I$5=D$4),Phase1_ALE!$A$5&" ","")&IF(AND(Phase1_ALE!$H$6=$A6,Phase1_ALE!$I$6=D$4),Phase1_ALE!$A$6&" ","")&IF(AND(Phase1_ALE!$H$7=$A6,Phase1_ALE!$I$7=D$4),Phase1_ALE!$A$7&" ","")) -> F2 | F6: =Phase1_ALE!A6&" - "&Phase1_ALE!B6 -> F2 - Database Injection | G6: =Phase1_ALE!H6&" ("&TEXT(Phase1_ALE!D6,"0%")&")" -> Medium (25%) | H6: =Phase1_ALE!I6 -> High
A7: Low | B7: =TRIM(IF(AND(Phase1_ALE!$H$5=$A7,Phase1_ALE!$I$5=B$4),Phase1_ALE!$A$5&" ","")&IF(AND(Phase1_ALE!$H$6=$A7,Phase1_ALE!$I$6=B$4),Phase1_ALE!$A$6&" ","")&IF(AND(Phase1_ALE!$H$7=$A7,Phase1_ALE!$I$7=B$4),Phase1_ALE!$A$7&" ","")) | C7: =TRIM(IF(AND(Phase1_ALE!$H$5=$A7,Phase1_ALE!$I$5=C$4),Phase1_ALE!$A$5&" ","")&IF(AND(Phase1_ALE!$H$6=$A7,Phase1_ALE!$I$6=C$4),Phase1_ALE!$A$6&" ","")&IF(AND(Phase1_ALE!$H$7=$A7,Phase1_ALE!$I$7=C$4),Phase1_ALE!$A$7&" ","")) | D7: =TRIM(IF(AND(Phase1_ALE!$H$5=$A7,Phase1_ALE!$I$5=D$4),Phase1_ALE!$A$5&" ","")&IF(AND(Phase1_ALE!$H$6=$A7,Phase1_ALE!$I$6=D$4),Phase1_ALE!$A$6&" ","")&IF(AND(Phase1_ALE!$H$7=$A7,Phase1_ALE!$I$7=D$4),Phase1_ALE!$A$7&" ","")) | F7: =Phase1_ALE!A7&" - "&Phase1_ALE!B7 -> F3 - Session Hijacking | G7: =Phase1_ALE!H7&" ("&TEXT(Phase1_ALE!D7,"0%")&")" -> High (40%) | H7: =Phase1_ALE!I7 -> Medium
A9: Key: red = High risk, amber = Medium risk, green = Low risk. A finding ID appears in the cell where its probability and impact levels meet. | F9: Thresholds are the yellow cells on the Inputs sheet. Cell colours follow the standard 3x3 pattern.

Sheet Phase2_Controls
A1: Phase 2: Control cost-benefit analysis (Task 4)
A2: Risk reduction = ALE x effectiveness. ROI = (benefit - cost) / cost. Payback = initial investment / (annual risk reduction - annual maintenance).
A4: Control | B4: Mitigates | C4: Initial investment ($) | D4: Annual maintenance ($/yr) | E4: Effectiveness | F4: Inherent ALE of mitigated risk ($) | G4: Annual risk reduction ($) | H4: Residual ALE ($) | I4: Year-1 total cost ($) | J4: ROI on initial investment | K4: ROI on Year-1 total cost | L4: Annual net cash benefit ($) | M4: Payback (years) | N4: Payback (months) | O4: Payback (days) | P4: ROI rank (Year-1)
A5: =Inputs!B10 -> Advanced API Security Gateway | B5: =Inputs!F10 -> F1 | C5: =Inputs!C10 -> 350000 | D5: =Inputs!D10 -> 50000 | E5: =Inputs!E10 -> 0.9 | F5: =INDEX(Phase1_ALE!$E$5:$E$7,MATCH(B5,Phase1_ALE!$A$5:$A$7,0)) -> 750000 | G5: =F5*E5 -> 675000 | H5: =F5-G5 -> 75000 | I5: =C5+D5 -> 400000 | J5: =(G5-C5)/C5 -> 0.92857143 | K5: =(G5-I5)/I5 -> 0.6875 | L5: =G5-D5 -> 625000 | M5: =IF(L5>0,C5/L5,"n/a") -> 0.56 | N5: =IF(L5>0,M5*12,"n/a") -> 6.72 | O5: =IF(L5>0,M5*365,"n/a") -> 204.4 | P5: =RANK(K5,$K$5:$K$7,0) -> 3
A6: =Inputs!B11 -> Web Application Firewall (WAF) | B6: =Inputs!F11 -> F2 | C6: =Inputs!C11 -> 150000 | D6: =Inputs!D11 -> 25000 | E6: =Inputs!E11 -> 0.75 | F6: =INDEX(Phase1_ALE!$E$5:$E$7,MATCH(B6,Phase1_ALE!$A$5:$A$7,0)) -> 31250000 | G6: =F6*E6 -> 23437500 | H6: =F6-G6 -> 7812500 | I6: =C6+D6 -> 175000 | J6: =(G6-C6)/C6 -> 155.25 | K6: =(G6-I6)/I6 -> 132.92857 | L6: =G6-D6 -> 23412500 | M6: =IF(L6>0,C6/L6,"n/a") -> 0.006406834 | N6: =IF(L6>0,M6*12,"n/a") -> 0.076882007 | O6: =IF(L6>0,M6*365,"n/a") -> 2.3384944 | P6: =RANK(K6,$K$5:$K$7,0) -> 1
A7: =Inputs!B12 -> Multi-Factor Authentication Enhancement | B7: =Inputs!F12 -> F3 | C7: =Inputs!C12 -> 200000 | D7: =Inputs!D12 -> 30000 | E7: =Inputs!E12 -> 0.95 | F7: =INDEX(Phase1_ALE!$E$5:$E$7,MATCH(B7,Phase1_ALE!$A$5:$A$7,0)) -> 3000000 | G7: =F7*E7 -> 2850000 | H7: =F7-G7 -> 150000 | I7: =C7+D7 -> 230000 | J7: =(G7-C7)/C7 -> 13.25 | K7: =(G7-I7)/I7 -> 11.391304 | L7: =G7-D7 -> 2820000 | M7: =IF(L7>0,C7/L7,"n/a") -> 0.070921986 | N7: =IF(L7>0,M7*12,"n/a") -> 0.85106383 | O7: =IF(L7>0,M7*365,"n/a") -> 25.886525 | P7: =RANK(K7,$K$5:$K$7,0) -> 2
A8: Total portfolio | C8: =SUM(C5:C7) -> 700000 | D8: =SUM(D5:D7) -> 105000 | E8: =G8/F8 -> 0.77035714 | F8: =SUM(F5:F7) -> 35000000 | G8: =SUM(G5:G7) -> 26962500 | H8: =SUM(H5:H7) -> 8037500 | I8: =SUM(I5:I7) -> 805000 | J8: =(G8-C8)/C8 -> 37.517857 | K8: =(G8-I8)/I8 -> 32.493789 | L8: =SUM(L5:L7) -> 26857500 | M8: =IF(L8>0,C8/L8,"n/a") -> 0.026063483 | N8: =M8*12 -> 0.3127618 | O8: =M8*365 -> 9.5131714
A10: Portfolio effectiveness (E8) is the share of total inherent ALE removed. Each control is matched to one finding, so the portfolio inherent ALE equals the Phase 1 total.

Sheet Timeline
A1: Task 5: Risk reduction over time (3-year horizon, quarterly)
A2: Cost with controls = initial investment at day 0 + (residual ALE + maintenance) each year.
A4: Quarter after procurement | B4: Years | C4: Cumulative expected loss, no controls ($) | D4: Cumulative loss + control cost, with controls ($) | E4: Cumulative net benefit, total portfolio ($) | F4: API Gateway cumulative net ($) | G4: WAF cumulative net ($) | H4: MFA cumulative net ($)
A5: 0 | B5: =A5/4 -> 0 | C5: =Phase1_ALE!$E$8*B5 -> 0 | D5: =Phase2_Controls!$C$8+(Phase2_Controls!$H$8+Phase2_Controls!$D$8)*B5 -> 700000 | E5: =C5-D5 -> -700000 | F5: =-Phase2_Controls!$C$5+Phase2_Controls!$L$5*B5 -> -350000 | G5: =-Phase2_Controls!$C$6+Phase2_Controls!$L$6*B5 -> -150000 | H5: =-Phase2_Controls!$C$7+Phase2_Controls!$L$7*B5 -> -200000
A6: 1 | B6: =A6/4 -> 0.25 | C6: =Phase1_ALE!$E$8*B6 -> 8750000 | D6: =Phase2_Controls!$C$8+(Phase2_Controls!$H$8+Phase2_Controls!$D$8)*B6 -> 2735625 | E6: =C6-D6 -> 6014375 | F6: =-Phase2_Controls!$C$5+Phase2_Controls!$L$5*B6 -> -193750 | G6: =-Phase2_Controls!$C$6+Phase2_Controls!$L$6*B6 -> 5703125 | H6: =-Phase2_Controls!$C$7+Phase2_Controls!$L$7*B6 -> 505000
A7: 2 | B7: =A7/4 -> 0.5 | C7: =Phase1_ALE!$E$8*B7 -> 17500000 | D7: =Phase2_Controls!$C$8+(Phase2_Controls!$H$8+Phase2_Controls!$D$8)*B7 -> 4771250 | E7: =C7-D7 -> 12728750 | F7: =-Phase2_Controls!$C$5+Phase2_Controls!$L$5*B7 -> -37500 | G7: =-Phase2_Controls!$C$6+Phase2_Controls!$L$6*B7 -> 11556250 | H7: =-Phase2_Controls!$C$7+Phase2_Controls!$L$7*B7 -> 1210000
A8: 3 | B8: =A8/4 -> 0.75 | C8: =Phase1_ALE!$E$8*B8 -> 26250000 | D8: =Phase2_Controls!$C$8+(Phase2_Controls!$H$8+Phase2_Controls!$D$8)*B8 -> 6806875 | E8: =C8-D8 -> 19443125 | F8: =-Phase2_Controls!$C$5+Phase2_Controls!$L$5*B8 -> 118750 | G8: =-Phase2_Controls!$C$6+Phase2_Controls!$L$6*B8 -> 17409375 | H8: =-Phase2_Controls!$C$7+Phase2_Controls!$L$7*B8 -> 1915000
A9: 4 | B9: =A9/4 -> 1 | C9: =Phase1_ALE!$E$8*B9 -> 35000000 | D9: =Phase2_Controls!$C$8+(Phase2_Controls!$H$8+Phase2_Controls!$D$8)*B9 -> 8842500 | E9: =C9-D9 -> 26157500 | F9: =-Phase2_Controls!$C$5+Phase2_Controls!$L$5*B9 -> 275000 | G9: =-Phase2_Controls!$C$6+Phase2_Controls!$L$6*B9 -> 23262500 | H9: =-Phase2_Controls!$C$7+Phase2_Controls!$L$7*B9 -> 2620000
A10: 5 | B10: =A10/4 -> 1.25 | C10: =Phase1_ALE!$E$8*B10 -> 43750000 | D10: =Phase2_Controls!$C$8+(Phase2_Controls!$H$8+Phase2_Controls!$D$8)*B10 -> 10878125 | E10: =C10-D10 -> 32871875 | F10: =-Phase2_Controls!$C$5+Phase2_Controls!$L$5*B10 -> 431250 | G10: =-Phase2_Controls!$C$6+Phase2_Controls!$L$6*B10 -> 29115625 | H10: =-Phase2_Controls!$C$7+Phase2_Controls!$L$7*B10 -> 3325000
A11: 6 | B11: =A11/4 -> 1.5 | C11: =Phase1_ALE!$E$8*B11 -> 52500000 | D11: =Phase2_Controls!$C$8+(Phase2_Controls!$H$8+Phase2_Controls!$D$8)*B11 -> 12913750 | E11: =C11-D11 -> 39586250 | F11: =-Phase2_Controls!$C$5+Phase2_Controls!$L$5*B11 -> 587500 | G11: =-Phase2_Controls!$C$6+Phase2_Controls!$L$6*B11 -> 34968750 | H11: =-Phase2_Controls!$C$7+Phase2_Controls!$L$7*B11 -> 4030000
A12: 7 | B12: =A12/4 -> 1.75 | C12: =Phase1_ALE!$E$8*B12 -> 61250000 | D12: =Phase2_Controls!$C$8+(Phase2_Controls!$H$8+Phase2_Controls!$D$8)*B12 -> 14949375 | E12: =C12-D12 -> 46300625 | F12: =-Phase2_Controls!$C$5+Phase2_Controls!$L$5*B12 -> 743750 | G12: =-Phase2_Controls!$C$6+Phase2_Controls!$L$6*B12 -> 40821875 | H12: =-Phase2_Controls!$C$7+Phase2_Controls!$L$7*B12 -> 4735000
A13: 8 | B13: =A13/4 -> 2 | C13: =Phase1_ALE!$E$8*B13 -> 70000000 | D13: =Phase2_Controls!$C$8+(Phase2_Controls!$H$8+Phase2_Controls!$D$8)*B13 -> 16985000 | E13: =C13-D13 -> 53015000 | F13: =-Phase2_Controls!$C$5+Phase2_Controls!$L$5*B13 -> 900000 | G13: =-Phase2_Controls!$C$6+Phase2_Controls!$L$6*B13 -> 46675000 | H13: =-Phase2_Controls!$C$7+Phase2_Controls!$L$7*B13 -> 5440000
A14: 9 | B14: =A14/4 -> 2.25 | C14: =Phase1_ALE!$E$8*B14 -> 78750000 | D14: =Phase2_Controls!$C$8+(Phase2_Controls!$H$8+Phase2_Controls!$D$8)*B14 -> 19020625 | E14: =C14-D14 -> 59729375 | F14: =-Phase2_Controls!$C$5+Phase2_Controls!$L$5*B14 -> 1056250 | G14: =-Phase2_Controls!$C$6+Phase2_Controls!$L$6*B14 -> 52528125 | H14: =-Phase2_Controls!$C$7+Phase2_Controls!$L$7*B14 -> 6145000
A15: 10 | B15: =A15/4 -> 2.5 | C15: =Phase1_ALE!$E$8*B15 -> 87500000 | D15: =Phase2_Controls!$C$8+(Phase2_Controls!$H$8+Phase2_Controls!$D$8)*B15 -> 21056250 | E15: =C15-D15 -> 66443750 | F15: =-Phase2_Controls!$C$5+Phase2_Controls!$L$5*B15 -> 1212500 | G15: =-Phase2_Controls!$C$6+Phase2_Controls!$L$6*B15 -> 58381250 | H15: =-Phase2_Controls!$C$7+Phase2_Controls!$L$7*B15 -> 6850000
A16: 11 | B16: =A16/4 -> 2.75 | C16: =Phase1_ALE!$E$8*B16 -> 96250000 | D16: =Phase2_Controls!$C$8+(Phase2_Controls!$H$8+Phase2_Controls!$D$8)*B16 -> 23091875 | E16: =C16-D16 -> 73158125 | F16: =-Phase2_Controls!$C$5+Phase2_Controls!$L$5*B16 -> 1368750 | G16: =-Phase2_Controls!$C$6+Phase2_Controls!$L$6*B16 -> 64234375 | H16: =-Phase2_Controls!$C$7+Phase2_Controls!$L$7*B16 -> 7555000
A17: 12 | B17: =A17/4 -> 3 | C17: =Phase1_ALE!$E$8*B17 -> 105000000 | D17: =Phase2_Controls!$C$8+(Phase2_Controls!$H$8+Phase2_Controls!$D$8)*B17 -> 25127500 | E17: =C17-D17 -> 79872500 | F17: =-Phase2_Controls!$C$5+Phase2_Controls!$L$5*B17 -> 1525000 | G17: =-Phase2_Controls!$C$6+Phase2_Controls!$L$6*B17 -> 70087500 | H17: =-Phase2_Controls!$C$7+Phase2_Controls!$L$7*B17 -> 8260000
A20: Year-end summary
A21: Milestone | B21: Years elapsed | C21: Inherent ALE ($) | D21: Residual ALE ($) | E21: Cumulative cost ($) | F21: Cumulative saved ($) | G21: Cumulative net ($)
A22: Day 0 (procure) | B22: 0 | C22: =Phase1_ALE!$E$8 -> 35000000 | D22: =IF(B22=0,C22,Phase2_Controls!$H$8) -> 35000000 | E22: =Phase2_Controls!$C$8+Phase2_Controls!$D$8*B22 -> 700000 | F22: =Phase2_Controls!$G$8*B22 -> 0 | G22: =F22-E22 -> -700000
A23: End of Year 1 | B23: 1 | C23: =Phase1_ALE!$E$8 -> 35000000 | D23: =IF(B23=0,C23,Phase2_Controls!$H$8) -> 8037500 | E23: =Phase2_Controls!$C$8+Phase2_Controls!$D$8*B23 -> 805000 | F23: =Phase2_Controls!$G$8*B23 -> 26962500 | G23: =F23-E23 -> 26157500
A24: End of Year 2 | B24: 2 | C24: =Phase1_ALE!$E$8 -> 35000000 | D24: =IF(B24=0,C24,Phase2_Controls!$H$8) -> 8037500 | E24: =Phase2_Controls!$C$8+Phase2_Controls!$D$8*B24 -> 910000 | F24: =Phase2_Controls!$G$8*B24 -> 53925000 | G24: =F24-E24 -> 53015000
A25: End of Year 3 | B25: 3 | C25: =Phase1_ALE!$E$8 -> 35000000 | D25: =IF(B25=0,C25,Phase2_Controls!$H$8) -> 8037500 | E25: =Phase2_Controls!$C$8+Phase2_Controls!$D$8*B25 -> 1015000 | F25: =Phase2_Controls!$G$8*B25 -> 80887500 | G25: =F25-E25 -> 79872500

Sheet Budget
A1: Bonus: combined risk-control matrix and optimal selection under budget limits
A3: A. Every combination of the three controls (1 = selected, 0 = not selected)
A4: Combination | B4: API Gateway | C4: WAF | D4: MFA | E4: Total initial investment ($) | F4: Annual maintenance ($) | G4: Annual risk reduction ($) | H4: Residual ALE ($) | I4: Year-1 ROI
A5: None | B5: 0 | C5: 0 | D5: 0 | E5: =B5*Phase2_Controls!$C$5+C5*Phase2_Controls!$C$6+D5*Phase2_Controls!$C$7 -> 0 | F5: =B5*Phase2_Controls!$D$5+C5*Phase2_Controls!$D$6+D5*Phase2_Controls!$D$7 -> 0 | G5: =B5*Phase2_Controls!$G$5+C5*Phase2_Controls!$G$6+D5*Phase2_Controls!$G$7 -> 0 | H5: =Phase2_Controls!$F$8-G5 -> 35000000 | I5: =IF(E5>0,(G5-E5-F5)/(E5+F5),"n/a") -> n/a
A6: API Gateway only | B6: 1 | C6: 0 | D6: 0 | E6: =B6*Phase2_Controls!$C$5+C6*Phase2_Controls!$C$6+D6*Phase2_Controls!$C$7 -> 350000 | F6: =B6*Phase2_Controls!$D$5+C6*Phase2_Controls!$D$6+D6*Phase2_Controls!$D$7 -> 50000 | G6: =B6*Phase2_Controls!$G$5+C6*Phase2_Controls!$G$6+D6*Phase2_Controls!$G$7 -> 675000 | H6: =Phase2_Controls!$F$8-G6 -> 34325000 | I6: =IF(E6>0,(G6-E6-F6)/(E6+F6),"n/a") -> 0.6875
A7: WAF only | B7: 0 | C7: 1 | D7: 0 | E7: =B7*Phase2_Controls!$C$5+C7*Phase2_Controls!$C$6+D7*Phase2_Controls!$C$7 -> 150000 | F7: =B7*Phase2_Controls!$D$5+C7*Phase2_Controls!$D$6+D7*Phase2_Controls!$D$7 -> 25000 | G7: =B7*Phase2_Controls!$G$5+C7*Phase2_Controls!$G$6+D7*Phase2_Controls!$G$7 -> 23437500 | H7: =Phase2_Controls!$F$8-G7 -> 11562500 | I7: =IF(E7>0,(G7-E7-F7)/(E7+F7),"n/a") -> 132.92857
A8: MFA only | B8: 0 | C8: 0 | D8: 1 | E8: =B8*Phase2_Controls!$C$5+C8*Phase2_Controls!$C$6+D8*Phase2_Controls!$C$7 -> 200000 | F8: =B8*Phase2_Controls!$D$5+C8*Phase2_Controls!$D$6+D8*Phase2_Controls!$D$7 -> 30000 | G8: =B8*Phase2_Controls!$G$5+C8*Phase2_Controls!$G$6+D8*Phase2_Controls!$G$7 -> 2850000 | H8: =Phase2_Controls!$F$8-G8 -> 32150000 | I8: =IF(E8>0,(G8-E8-F8)/(E8+F8),"n/a") -> 11.391304
A9: API Gateway + WAF | B9: 1 | C9: 1 | D9: 0 | E9: =B9*Phase2_Controls!$C$5+C9*Phase2_Controls!$C$6+D9*Phase2_Controls!$C$7 -> 500000 | F9: =B9*Phase2_Controls!$D$5+C9*Phase2_Controls!$D$6+D9*Phase2_Controls!$D$7 -> 75000 | G9: =B9*Phase2_Controls!$G$5+C9*Phase2_Controls!$G$6+D9*Phase2_Controls!$G$7 -> 24112500 | H9: =Phase2_Controls!$F$8-G9 -> 10887500 | I9: =IF(E9>0,(G9-E9-F9)/(E9+F9),"n/a") -> 40.934783
A10: API Gateway + MFA | B10: 1 | C10: 0 | D10: 1 | E10: =B10*Phase2_Controls!$C$5+C10*Phase2_Controls!$C$6+D10*Phase2_Controls!$C$7 -> 550000 | F10: =B10*Phase2_Controls!$D$5+C10*Phase2_Controls!$D$6+D10*Phase2_Controls!$D$7 -> 80000 | G10: =B10*Phase2_Controls!$G$5+C10*Phase2_Controls!$G$6+D10*Phase2_Controls!$G$7 -> 3525000 | H10: =Phase2_Controls!$F$8-G10 -> 31475000 | I10: =IF(E10>0,(G10-E10-F10)/(E10+F10),"n/a") -> 4.5952381
A11: WAF + MFA | B11: 0 | C11: 1 | D11: 1 | E11: =B11*Phase2_Controls!$C$5+C11*Phase2_Controls!$C$6+D11*Phase2_Controls!$C$7 -> 350000 | F11: =B11*Phase2_Controls!$D$5+C11*Phase2_Controls!$D$6+D11*Phase2_Controls!$D$7 -> 55000 | G11: =B11*Phase2_Controls!$G$5+C11*Phase2_Controls!$G$6+D11*Phase2_Controls!$G$7 -> 26287500 | H11: =Phase2_Controls!$F$8-G11 -> 8712500 | I11: =IF(E11>0,(G11-E11-F11)/(E11+F11),"n/a") -> 63.907407
A12: All three controls | B12: 1 | C12: 1 | D12: 1 | E12: =B12*Phase2_Controls!$C$5+C12*Phase2_Controls!$C$6+D12*Phase2_Controls!$C$7 -> 700000 | F12: =B12*Phase2_Controls!$D$5+C12*Phase2_Controls!$D$6+D12*Phase2_Controls!$D$7 -> 105000 | G12: =B12*Phase2_Controls!$G$5+C12*Phase2_Controls!$G$6+D12*Phase2_Controls!$G$7 -> 26962500 | H12: =Phase2_Controls!$F$8-G12 -> 8037500 | I12: =IF(E12>0,(G12-E12-F12)/(E12+F12),"n/a") -> 32.493789
A15: B. Best choice for each budget (initial investment limit)
A16: Budget limit ($) | B16: Best annual risk reduction ($) | C16: Selected combination | D16: Initial investment used ($) | E16: Unspent budget ($) | F16: Share of maximum reduction
A17: 150000 | B17: =_xlfn.MAXIFS($G$5:$G$12,$E$5:$E$12,"<="&A17) -> 23437500 | C17: =INDEX($A$5:$A$12,MATCH(B17,$G$5:$G$12,0)) -> WAF only | D17: =INDEX($E$5:$E$12,MATCH(B17,$G$5:$G$12,0)) -> 150000 | E17: =A17-D17 -> 0 | F17: =B17/MAX($G$5:$G$12) -> 0.86926287
A18: 200000 | B18: =_xlfn.MAXIFS($G$5:$G$12,$E$5:$E$12,"<="&A18) -> 23437500 | C18: =INDEX($A$5:$A$12,MATCH(B18,$G$5:$G$12,0)) -> WAF only | D18: =INDEX($E$5:$E$12,MATCH(B18,$G$5:$G$12,0)) -> 150000 | E18: =A18-D18 -> 50000 | F18: =B18/MAX($G$5:$G$12) -> 0.86926287
A19: 350000 | B19: =_xlfn.MAXIFS($G$5:$G$12,$E$5:$E$12,"<="&A19) -> 26287500 | C19: =INDEX($A$5:$A$12,MATCH(B19,$G$5:$G$12,0)) -> WAF + MFA | D19: =INDEX($E$5:$E$12,MATCH(B19,$G$5:$G$12,0)) -> 350000 | E19: =A19-D19 -> 0 | F19: =B19/MAX($G$5:$G$12) -> 0.97496523
A20: =Inputs!B22 -> 500000 | B20: =_xlfn.MAXIFS($G$5:$G$12,$E$5:$E$12,"<="&A20) -> 26287500 | C20: =INDEX($A$5:$A$12,MATCH(B20,$G$5:$G$12,0)) -> WAF + MFA | D20: =INDEX($E$5:$E$12,MATCH(B20,$G$5:$G$12,0)) -> 350000 | E20: =A20-D20 -> 150000 | F20: =B20/MAX($G$5:$G$12) -> 0.97496523
A21: 550000 | B21: =_xlfn.MAXIFS($G$5:$G$12,$E$5:$E$12,"<="&A21) -> 26287500 | C21: =INDEX($A$5:$A$12,MATCH(B21,$G$5:$G$12,0)) -> WAF + MFA | D21: =INDEX($E$5:$E$12,MATCH(B21,$G$5:$G$12,0)) -> 350000 | E21: =A21-D21 -> 200000 | F21: =B21/MAX($G$5:$G$12) -> 0.97496523
A22: 700000 | B22: =_xlfn.MAXIFS($G$5:$G$12,$E$5:$E$12,"<="&A22) -> 26962500 | C22: =INDEX($A$5:$A$12,MATCH(B22,$G$5:$G$12,0)) -> All three controls | D22: =INDEX($E$5:$E$12,MATCH(B22,$G$5:$G$12,0)) -> 700000 | E22: =A22-D22 -> 0 | F22: =B22/MAX($G$5:$G$12) -> 1
A25: C. Combined risk-control matrix
A26: Vulnerability | B26: Control | C26: Current ALE ($) | D26: Residual ALE ($) | E26: Control cost, initial ($) | F26: Annual benefit ($) | G26: Year-1 net benefit ($) | H26: Year-1 ROI
A27: =Phase1_ALE!B5 -> API Authentication Bypass | B27: =Phase2_Controls!A5 -> Advanced API Security Gateway | C27: =Phase2_Controls!F5 -> 750000 | D27: =Phase2_Controls!H5 -> 75000 | E27: =Phase2_Controls!C5 -> 350000 | F27: =Phase2_Controls!G5 -> 675000 | G27: =Phase2_Controls!G5-Phase2_Controls!I5 -> 275000 | H27: =Phase2_Controls!K5 -> 0.6875
A28: =Phase1_ALE!B6 -> Database Injection | B28: =Phase2_Controls!A6 -> Web Application Firewall (WAF) | C28: =Phase2_Controls!F6 -> 31250000 | D28: =Phase2_Controls!H6 -> 7812500 | E28: =Phase2_Controls!C6 -> 150000 | F28: =Phase2_Controls!G6 -> 23437500 | G28: =Phase2_Controls!G6-Phase2_Controls!I6 -> 23262500 | H28: =Phase2_Controls!K6 -> 132.92857
A29: =Phase1_ALE!B7 -> Session Hijacking | B29: =Phase2_Controls!A7 -> Multi-Factor Authentication Enhancement | C29: =Phase2_Controls!F7 -> 3000000 | D29: =Phase2_Controls!H7 -> 150000 | E29: =Phase2_Controls!C7 -> 200000 | F29: =Phase2_Controls!G7 -> 2850000 | G29: =Phase2_Controls!G7-Phase2_Controls!I7 -> 2620000 | H29: =Phase2_Controls!K7 -> 11.391304
A30: Total | C30: =SUM(C27:C29) -> 35000000 | D30: =SUM(D27:D29) -> 8037500 | E30: =SUM(E27:E29) -> 700000 | F30: =SUM(F27:F29) -> 26962500 | G30: =SUM(G27:G29) -> 26157500

Sheet Gantt
A1: Task 7: Risk treatment timeline (Gantt)
A2: Analyst proposal. Days count from approval. Budget per task adds up to the total initial investment.
A4: Task | B4: Phase | C4: Start day | D4: End day | E4: Duration (days) | F4: Budget ($) | G4: Accountable lead | H4: Offset (chart helper) | I4: Immediate (0-30d) | J4: Short-term (31-90d) | K4: Long-term (91-365d)
A5: SQLi virtual patching and input sanitization | B5: Immediate | C5: 1 | D5: 10 | E5: =D5-C5+1 -> 10 | F5: 0 | G5: SecOps Engineering | H5: =C5-1 -> 0 | I5: =IF(B5="Immediate",E5,0) -> 10 | J5: =IF(B5="Short-term",E5,0) -> 0 | K5: =IF(B5="Long-term",E5,0) -> 0
A6: WAF procurement and deployment | B6: Immediate | C6: 11 | D6: 20 | E6: =D6-C6+1 -> 10 | F6: 150000 | G6: Infrastructure / SecOps | H6: =C6-1 -> 10 | I6: =IF(B6="Immediate",E6,0) -> 10 | J6: =IF(B6="Short-term",E6,0) -> 0 | K6: =IF(B6="Long-term",E6,0) -> 0
A7: Session hardening (15-min timeout, login limits) | B7: Immediate | C7: 21 | D7: 30 | E7: =D7-C7+1 -> 10 | F7: 0 | G7: AppSec Team | H7: =C7-1 -> 20 | I7: =IF(B7="Immediate",E7,0) -> 10 | J7: =IF(B7="Short-term",E7,0) -> 0 | K7: =IF(B7="Long-term",E7,0) -> 0
A8: MFA enhancement rollout | B8: Short-term | C8: 31 | D8: 60 | E8: =D8-C8+1 -> 30 | F8: 200000 | G8: IAM and Identity Lead | H8: =C8-1 -> 30 | I8: =IF(B8="Immediate",E8,0) -> 0 | J8: =IF(B8="Short-term",E8,0) -> 30 | K8: =IF(B8="Long-term",E8,0) -> 0
A9: API gateway proof of concept and architecture | B9: Short-term | C9: 61 | D9: 90 | E9: =D9-C9+1 -> 30 | F9: 50000 | G9: Architecture and GRC | H9: =C9-1 -> 60 | I9: =IF(B9="Immediate",E9,0) -> 0 | J9: =IF(B9="Short-term",E9,0) -> 30 | K9: =IF(B9="Long-term",E9,0) -> 0
A10: API gateway production cutover | B10: Long-term | C10: 91 | D10: 270 | E10: =D10-C10+1 -> 180 | F10: 300000 | G10: CISO and Lead GRC Analyst | H10: =C10-1 -> 90 | I10: =IF(B10="Immediate",E10,0) -> 0 | J10: =IF(B10="Short-term",E10,0) -> 0 | K10: =IF(B10="Long-term",E10,0) -> 180
A11: Continuous monitoring and quarterly testing | B11: Long-term | C11: 91 | D11: 365 | E11: =D11-C11+1 -> 275 | F11: 0 | G11: SecOps Engineering | H11: =C11-1 -> 90 | I11: =IF(B11="Immediate",E11,0) -> 0 | J11: =IF(B11="Short-term",E11,0) -> 0 | K11: =IF(B11="Long-term",E11,0) -> 275
A12: Re-audit and risk re-quantification | B12: Long-term | C12: 300 | D12: 365 | E12: =D12-C12+1 -> 66 | F12: 0 | G12: Lead GRC Analyst | H12: =C12-1 -> 299 | I12: =IF(B12="Immediate",E12,0) -> 0 | J12: =IF(B12="Short-term",E12,0) -> 0 | K12: =IF(B12="Long-term",E12,0) -> 66
A13: Total budget | F13: =SUM(F5:F12) -> 700000
A14: Check against total initial investment (should be 0) | F14: =F13-Phase2_Controls!C8 -> 0

Sheet Charts
A1: Required graphs (all linked to the calculation sheets)
